ttkbootstrap_icons/__init__.py
ttkbootstrap_icons/_version.py
ttkbootstrap_icons/browser.py
ttkbootstrap_icons/icon.py
ttkbootstrap_icons/providers.py
ttkbootstrap_icons/registry.py
ttkbootstrap_icons/stateful_icon_mixin.py
ttkbootstrap_icons/tooling.py
ttkbootstrap_icons/_pyinstaller/__init__.py
ttkbootstrap_icons/_pyinstaller/hook-ttkbootstrap_icons.py
ttkbootstrap_icons/_pyinstaller/hook-ttkbootstrap_icons_devicon.py
ttkbootstrap_icons/_pyinstaller/hook-ttkbootstrap_icons_eva.py
ttkbootstrap_icons/_pyinstaller/hook-ttkbootstrap_icons_fa.py
ttkbootstrap_icons/_pyinstaller/hook-ttkbootstrap_icons_fluent.py
ttkbootstrap_icons/_pyinstaller/hook-ttkbootstrap_icons_gmi.py
ttkbootstrap_icons/_pyinstaller/hook-ttkbootstrap_icons_ion.py
ttkbootstrap_icons/_pyinstaller/hook-ttkbootstrap_icons_lucide.py
ttkbootstrap_icons/_pyinstaller/hook-ttkbootstrap_icons_mat.py
ttkbootstrap_icons/_pyinstaller/hook-ttkbootstrap_icons_meteocons.py
ttkbootstrap_icons/_pyinstaller/hook-ttkbootstrap_icons_remix.py
ttkbootstrap_icons/_pyinstaller/hook-ttkbootstrap_icons_rpga.py
ttkbootstrap_icons/_pyinstaller/hook-ttkbootstrap_icons_simple.py
ttkbootstrap_icons/_pyinstaller/hook-ttkbootstrap_icons_typicons.py
ttkbootstrap_icons/_pyinstaller/hook-ttkbootstrap_icons_weather.py
ttkbootstrap_icons/assets/__init__.py
ttkbootstrap_icons/assets/__pycache__/__init__.cpython-313.pyc
ttkbootstrap_icons/tools/build_all.py
ttkbootstrap_icons-4.0.0.dist-info/METADATA
ttkbootstrap_icons-4.0.0.dist-info/WHEEL
ttkbootstrap_icons-4.0.0.dist-info/entry_points.txt
ttkbootstrap_icons-4.0.0.dist-info/top_level.txt
ttkbootstrap_icons-4.0.0.dist-info/RECORD
