Metadata-Version: 2.4
Name: ttkbootstrap-icons
Version: 4.0.0
Summary: Base package for font-based icons in Tkinter/ttkbootstrap with installable icon providers: Bootstrap, Font Awesome, Material, Ionicons, Remix, Fluent, Simple, Weather, Lucide, Eva & more.
Author-email: Israel Dryer <israel.dryer@gmail.com>
License-Expression: MIT
Project-URL: Homepage, https://github.com/israel-dryer/ttkbootstrap-icons
Keywords: tkinter,ttk,bootstrap,gui,desktop,python3,ui,widgets,theming,cross-platform,modern,responsive,python-gui,icon
Classifier: Development Status :: 5 - Production/Stable
Classifier: Environment :: Win32 (MS Windows)
Classifier: Environment :: X11 Applications :: GTK
Classifier: Intended Audience :: Developers
Classifier: Programming Language :: Python :: 3
Classifier: Programming Language :: Python :: 3.10
Classifier: Programming Language :: Python :: 3.11
Classifier: Programming Language :: Python :: 3.12
Classifier: Programming Language :: Python :: 3.13
Classifier: Topic :: Software Development :: User Interfaces
Classifier: Operating System :: OS Independent
Requires-Python: >=3.10
Requires-Dist: pillow>=9.1.0
Requires-Dist: typing-extensions>=4.7.1
